topplot/__init__.py
topplot/__main__.py
topplot/app.py
topplot/config.py
topplot/dataframes.py
topplot/figman.py
topplot/graphmap.py
topplot/gui_utils.py
topplot/linestyler.py
topplot/logo.png
topplot/profiler.py
topplot/progress_window.py
topplot/rcparams.py
topplot/tempfile.py
topplot/toptype.py
topplot/utils.py
topplot/graphs/__init__.py
topplot/graphs/_cpus.py
topplot/graphs/_legends.py
topplot/graphs/_mem.py
topplot/graphs/_overview.py
topplot/graphs/_poi.py
topplot/graphs/_tasks.py
topplot/parser/__init__.py
topplot/parser/_list_processes.py
topplot/parser/_munge.py
topplot/parser/_regex.py
topplot/parser/re_variants.py
topplot/parser/topndict.py
topplot-0.2.1.dist-info/LICENCE
topplot-0.2.1.dist-info/METADATA
topplot-0.2.1.dist-info/WHEEL
topplot-0.2.1.dist-info/entry_points.txt
topplot-0.2.1.dist-info/top_level.txt
topplot-0.2.1.dist-info/RECORD
