Metadata-Version: 2.1
Name: topplot
Version: 0.2.1
Summary: Munge top logs in to graph
Home-page: https://gitlab.com/ebardie/topplot
Author: Jonathan Sambrook
Author-email: ebardie@gmail.com
License: GPLv3
Project-URL: Bug Tracker, https://gitlab.com/ebardie/topplot/issues
Project-URL: Changelog, https://gitlab.com/ebardie/topplot/blob/master/RELEASE.md
Keywords: top,graphs
Platform: Linux
Platform: Windows
Classifier: Programming Language :: Python :: 3
Classifier: License :: OSI Approved :: GNU General Public License v3 or later (GPLv3+)
Classifier: Operating System :: OS Independent
Classifier: Development Status :: 3 - Alpha
Classifier: Environment :: X11 Applications
Classifier: Intended Audience :: System Administrators
Classifier: Intended Audience :: Developers
Classifier: Operating System :: POSIX
Classifier: Operating System :: POSIX :: Linux
Classifier: Topic :: System :: Logging
Classifier: Topic :: System :: Monitoring
Requires-Python: >=3.9
License-File: LICENCE
Requires-Dist: pip (>=21)
Requires-Dist: setuptools (>=60)
Requires-Dist: matplotlib (>=3.3.3)
Requires-Dist: mplcursors
Requires-Dist: pandas
Requires-Dist: screeninfo
